setup.py
aiptest/Assert.py
aiptest/Consts.py
aiptest/Logs.py
aiptest/__init__.py
aiptest/api.py
aiptest/check_expectation.py
aiptest/data_entry.py
aiptest/excel2case.py
aiptest/function.py
aiptest/global_data_warehouse.py
aiptest/httpxyz.py
aiptest/loggers.py
aiptest/version.py
aiptest.egg-info/PKG-INFO
aiptest.egg-info/SOURCES.txt
aiptest.egg-info/dependency_links.txt
aiptest.egg-info/requires.txt
aiptest.egg-info/top_level.txt