Metadata-Version: 2.1
Name: aiptest
Version: 0.0.1
Summary: pytest接口测试
Home-page: https://gitee.com/zrr/apitest
Author: zrr
Author-email: 781103544@qq.com
License: UNKNOWN
Platform: UNKNOWN
Requires-Python: >=3.7
